adofaihelper/__init__.py
adofaihelper/action.py
adofaihelper/decoration.py
adofaihelper/enums.py
adofaihelper/settings.py
adofaihelper-1.1.7.dist-info/METADATA
adofaihelper-1.1.7.dist-info/WHEEL
adofaihelper-1.1.7.dist-info/top_level.txt
adofaihelper-1.1.7.dist-info/RECORD
