Metadata-Version: 2.1
Name: adofaihelper
Version: 1.1.7
Summary: A module to process adofai file
Author: Lipcu
Author-email: li-p-cu@outlook.com
